[{"email":"Candice_Ortiz@gmail.com","password":"yidubami","passwordHash":"$argon2i$v=19$m=4096,t=3,p=1$xSwJdKyWRbvvQisoP6p9ZA$jdqBqyVtXjmxae98SPnFHF+q6Rb5QTkitXK/MAbfXzo","givenName":"Candice","familyName":"Ortiz","profileDescription":"Use the mobile TCP array, then you can quantify the bluetooth program!"},{"email":"David37@hotmail.com","password":"muyepabo","passwordHash":"$argon2i$v=19$m=4096,t=3,p=1$BNBMo/8NUURymmJuut/77A$mAzWZrt0ZLCpw9cIkgztY/ELYr5gtBdEhQ9FB2WQOXE","givenName":"David","familyName":"Rempel","profileDescription":"If we parse the feed, we can get to the SMTP application through the haptic FTP microchip!"},{"email":"Bryon.Reinger17@hotmail.com","password":"juyuzuxe","passwordHash":"$argon2i$v=19$m=4096,t=3,p=1$DKdyAzwJVzP+2dpUMoNKoA$/tV+SK74JpK9Cf5pIWwPUvuIoln/uk6Bun6XDgrxhy0","givenName":"Bryon","familyName":"Reinger","profileDescription":"Try to connect the AGP hard drive, maybe it will navigate the multi-byte panel!"},{"email":"Ludie.Gibson83@yahoo.com","password":"genehaco","passwordHash":"$argon2i$v=19$m=4096,t=3,p=1$INexg6hjU9Emn3UKPPc8AA$HCpqfvEGtR2sFSJ05uzBRIjftUu0Q0q2Hi6wIgAvqUI","givenName":"Ludie","familyName":"Gibson","profileDescription":"We need to synthesize the cross-platform HTTP alarm!"},{"email":"Adolph.Bradtke@hotmail.com","password":"lebizefe","passwordHash":"$argon2i$v=19$m=4096,t=3,p=1$qXAmikHNXxW+oR+gGq77jg$zBTfSRHEqiznZHj0B92u0abWO48ttTF8/CUE2Ydl4K8","givenName":"Adolph","familyName":"Bradtke","profileDescription":"The RSS bandwidth is down, navigate the open-source hard drive so we can quantify the RAM port!"},{"email":"Aurelia95@yahoo.com","password":"hoxumejo","passwordHash":"$argon2i$v=19$m=4096,t=3,p=1$qh7SMfA2JRaXr9++iOVSzg$hNq7jGeAoP8Brp6MOVYMpC/tkJoWEh2nU+HpvFAr/xw","givenName":"Aurelia","familyName":"Paucek","profileDescription":"If we reboot the feed, we can get to the TCP protocol through the auxiliary IB port!"},{"email":"Leslie96@yahoo.com","password":"mobaboxi","passwordHash":"$argon2i$v=19$m=4096,t=3,p=1$pxvuZ0+aWUrrWFiGUZQK4w$a/7Ajoa35xH2G3AApkDkeM+ZeDsjVa6YJkSS+Gv1lZs","givenName":"Leslie","familyName":"Torphy","profileDescription":"I'll connect the digital ADP card, that should matrix the USB bandwidth!"},{"email":"Lillie81@gmail.com","password":"sodogexo","passwordHash":"$argon2i$v=19$m=4096,t=3,p=1$e64XUo0YJzubqAWtid2ZwQ$7Md0pfAyZHc6h8RyfcfjbHoAdys2ulwWVAt2oFLSKDI","givenName":"Lillie","familyName":"Hilll","profileDescription":"The COM driver is down, reboot the online monitor so we can input the FTP firewall!"},{"email":"Shaylee.Hermann@gmail.com","password":"vatinuya","passwordHash":"$argon2i$v=19$m=4096,t=3,p=1$P7Y+/Ofj2jZPdkTEYfw8qQ$s5AqzKZdoLgIl+cdAqn/ekdNNKpQBf8E9OkrkTKE4oY","givenName":"Shaylee","familyName":"Hermann","profileDescription":"backing up the alarm won't do anything, we need to connect the solid state SMTP monitor!"},{"email":"Rowan.Konopelski@hotmail.com","password":"tekofuya","passwordHash":"$argon2i$v=19$m=4096,t=3,p=1$xkPR1sD4zFQa6jEYhcX8Yg$KM/Joq8HLc+lnbXLJN4wNNYKh1XuV32iZTDLyXnNWqU","givenName":"Rowan","familyName":"Konopelski","profileDescription":"Use the wireless AGP interface, then you can connect the mobile monitor!"}]